terobot/__index__.py
terobot/__init__.py
terobot/client.py
terobot-1.0.1.dist-info/METADATA
terobot-1.0.1.dist-info/WHEEL
terobot-1.0.1.dist-info/top_level.txt
terobot-1.0.1.dist-info/RECORD
