Metadata-Version: 2.1
Name: terobot
Version: 1.0.1
Summary: TeroBot Python client
Author-email: Lobelia Earth <info@lobelia.earth>
License: MIT
Requires-Python: >=3.10
Requires-Dist: requests >=2.32.1
